[
  {
    "filename": "angles-placeholder-01.jpg",
    "tags": [
      "window",
      "geometry",
      "light",
      "urban"
    ],
    "alt": "Placeholder image for the Angles archive",
    "sourceHash": "1037eb841ff517bde76f65fa37d7de7980ce0928"
  },
  {
    "filename": "angles-placeholder-02.jpg",
    "tags": [
      "window",
      "reflection",
      "urban",
      "night"
    ],
    "alt": "Placeholder image for the Angles archive",
    "sourceHash": "1037eb841ff517bde76f65fa37d7de7980ce0928"
  },
  {
    "filename": "angles-placeholder-03.jpg",
    "tags": [
      "portrait",
      "shadow",
      "light",
      "interior"
    ],
    "alt": "Placeholder image for the Angles archive",
    "sourceHash": "1037eb841ff517bde76f65fa37d7de7980ce0928"
  },
  {
    "filename": "angles-placeholder-04.jpg",
    "tags": [
      "portrait",
      "shadow",
      "gesture",
      "night"
    ],
    "alt": "Placeholder image for the Angles archive",
    "sourceHash": "1037eb841ff517bde76f65fa37d7de7980ce0928"
  },
  {
    "filename": "angles-placeholder-05.jpg",
    "tags": [
      "geometry",
      "pattern",
      "facade",
      "urban"
    ],
    "alt": "Placeholder image for the Angles archive",
    "sourceHash": "1037eb841ff517bde76f65fa37d7de7980ce0928"
  },
  {
    "filename": "angles-placeholder-06.jpg",
    "tags": [
      "pattern",
      "shadow",
      "black-and-white",
      "window"
    ],
    "alt": "Placeholder image for the Angles archive",
    "sourceHash": "1037eb841ff517bde76f65fa37d7de7980ce0928"
  },
  {
    "filename": "angles-placeholder-07.jpg",
    "tags": [
      "nature",
      "texture",
      "light",
      "detail"
    ],
    "alt": "Placeholder image for the Angles archive",
    "sourceHash": "1037eb841ff517bde76f65fa37d7de7980ce0928"
  },
  {
    "filename": "angles-placeholder-08.jpg",
    "tags": [
      "nature",
      "reflection",
      "detail",
      "water"
    ],
    "alt": "Placeholder image for the Angles archive",
    "sourceHash": "1037eb841ff517bde76f65fa37d7de7980ce0928"
  },
  {
    "filename": "angles-placeholder-09.jpg",
    "tags": [
      "black-and-white",
      "urban",
      "facade",
      "contrast"
    ],
    "alt": "Placeholder image for the Angles archive",
    "sourceHash": "1037eb841ff517bde76f65fa37d7de7980ce0928"
  },
  {
    "filename": "angles-placeholder-10.jpg",
    "tags": [
      "contrast",
      "shadow",
      "geometry",
      "detail"
    ],
    "alt": "Placeholder image for the Angles archive",
    "sourceHash": "1037eb841ff517bde76f65fa37d7de7980ce0928"
  },
  {
    "filename": "angles-placeholder-11.jpg",
    "tags": [
      "portrait",
      "reflection",
      "window",
      "contrast"
    ],
    "alt": "Placeholder image for the Angles archive",
    "sourceHash": "1037eb841ff517bde76f65fa37d7de7980ce0928"
  },
  {
    "filename": "angles-placeholder-12.jpg",
    "tags": [
      "water",
      "pattern",
      "light",
      "night"
    ],
    "alt": "Placeholder image for the Angles archive",
    "sourceHash": "1037eb841ff517bde76f65fa37d7de7980ce0928"
  }
]
